jwt_manager/__init__.py
jwt_manager/application/__init__.py
jwt_manager/application/config.py
jwt_manager/application/jwt_service.py
jwt_manager/domain/__init__.py
jwt_manager/domain/models.py
jwt_manager/domain/repositories.py
jwt_manager/domain/services.py
jwt_manager/exceptions/__init__.py
jwt_manager/exceptions/custom_exceptions.py
jwt_manager/infrastructure/__init__.py
jwt_manager/infrastructure/database.py
jwt_manager/infrastructure/header_parser.py
tests/__init__.py
tests/test_exceptions.py
tests/test_header_parser.py
tests/test_jwt_service.py
tests/test_models.py
tests/test_services.py
marfyl_jwt_manager-0.22.0.dist-info/METADATA
marfyl_jwt_manager-0.22.0.dist-info/WHEEL
marfyl_jwt_manager-0.22.0.dist-info/top_level.txt
marfyl_jwt_manager-0.22.0.dist-info/RECORD
