Metadata-Version: 2.1
Name: marfyl-jwt-manager
Version: 0.22.0
Summary: A service to process jwt from headers
Author: Eduardo Ponce
Author-email: poncejones@gmail.com
Requires-Python: >=3.9
Requires-Dist: PyJWT
Requires-Dist: cryptography
Requires-Dist: fastapi
Requires-Dist: starlette
Requires-Dist: python-dotenv
